tevclient/__init__.py
tevclient/packet.py
tevclient-1.0.3.dist-info/licenses/LICENSE.txt
tevclient-1.0.3.dist-info/METADATA
tevclient-1.0.3.dist-info/WHEEL
tevclient-1.0.3.dist-info/top_level.txt
tevclient-1.0.3.dist-info/RECORD
