Metadata-Version: 2.4
Name: tevclient
Version: 1.0.3
Summary: Module for remote-controlling the tev image viewer.
Author-email: Thomas Müller <tom@94.me>
License-Expression: BSD-3-Clause
Project-URL: Repository, https://github.com/Tom94/tevclient
Classifier: Development Status :: 5 - Production/Stable
Classifier: Intended Audience :: Developers
Classifier: Topic :: Software Development :: Libraries :: Python Modules
Classifier: Programming Language :: Python :: 3.11
Classifier: Programming Language :: Python :: 3.12
Classifier: Programming Language :: Python :: 3.13
Classifier: Programming Language :: Python :: 3.14
Classifier: Operating System :: OS Independent
Requires-Python: >=3.11
License-File: LICENSE.txt
Requires-Dist: numpy
Dynamic: license-file
